sdf/__init__.py
sdf/core.py
sdf/d2.py
sdf/d3.py
sdf/dn.py
sdf/ease.py
sdf/mesh.py
sdf/progress.py
sdf/stl.py
sdf/text.py
sdf/util.py
unitcellsdf-0.0.2.dist-info/METADATA
unitcellsdf-0.0.2.dist-info/WHEEL
unitcellsdf-0.0.2.dist-info/licenses/LICENSE.md
unitcellsdf-0.0.2.dist-info/RECORD
