Metadata-Version: 2.3
Name: unitcellsdf
Version: 0.0.2
Summary: Generate 3D meshes from signed distance functions.
Project-URL: Homepage, https://github.com/unitcellhub/unitcellsdf
Project-URL: Bug Reports, https://github.com/unitcellhub/unitcellsdf/issues
Author-email: Michael Fogleman <michael.fogleman@gmail.com>
License: Copyright (C) 2021 Michael Fogleman
Keywords: sdf,unitcell,unitcellhub
Classifier: Development Status :: 3 - Alpha
Classifier: Intended Audience :: Developers
Classifier: License :: OSI Approved :: MIT License
Classifier: Natural Language :: English
Classifier: Programming Language :: Python
Classifier: Programming Language :: Python :: 3
Requires-Python: >=3.9
Requires-Dist: matplotlib>=3.9.3
Requires-Dist: meshio>=5.3.5
Requires-Dist: numpy<2.0
Requires-Dist: pillow>=11.0.0
Requires-Dist: scikit-image>=0.24.0
Requires-Dist: scipy>=1.13.1
